pyhashsum/__init__.py
pyhashsum/main.py
pyhashsum-3.5.1.dist-info/LICENSE
pyhashsum-3.5.1.dist-info/METADATA
pyhashsum-3.5.1.dist-info/WHEEL
pyhashsum-3.5.1.dist-info/entry_points.txt
pyhashsum-3.5.1.dist-info/top_level.txt
pyhashsum-3.5.1.dist-info/RECORD
