Metadata-Version: 2.2
Name: pyhashsum
Version: 3.5.1
Summary: Cross-platform file integrity verification tool with modern GUI
Home-page: https://github.com/oop7/pyhashsum
Author: oop7
Author-email: oop7 <oop7_support@proton.me>
License: MIT License
Project-URL: Homepage, https://github.com/oop7/pyhashsum
Project-URL: Bug Tracker, https://github.com/oop7/pyhashsum/issues
Requires-Python: >=3.7
License-File: LICENSE
Requires-Dist: PySide6
Requires-Dist: Pillow
Requires-Dist: packaging
Dynamic: author
Dynamic: home-page
Dynamic: requires-python
